pypeims/__about__.py
pypeims/__init__.py
pypeims/data/Special Education Funding Gap/SPED data request_SY2021_3.6.2023_ORIGINAL.xlsx
pypeims/data/Special Education Funding Gap/SPED data request_SY2022_3.14.2023_ORIGINAL.xls
pypeims/data/Special Education Funding Gap/SPED data request_SY2022_3.14.2023_PROCESSED.xlsx
pypeims/instruments/__init__.py
pypeims/instruments/utils.py
pypeims-0.0.31.dist-info/METADATA
pypeims-0.0.31.dist-info/WHEEL
pypeims-0.0.31.dist-info/licenses/LICENSE.txt
pypeims-0.0.31.dist-info/RECORD
